Workbook

Sheet Summary
A1: Options Appraisal Summary
A2: 5-year view. NPV at the Inputs discount rate. All values are formulas.
A4: Option | B4: NPV (€) | C4: IRR | D4: Payback (years) | E4: Year 0 investment (€) | F4: 5-yr benefits (€) | G4: 5-yr costs (€) | H4: Extra loans / yr
A5: A. Do nothing | B5: =Cash_Flows!B10+NPV(Inputs!$B$6,Cash_Flows!C10:G10) | C5: =IF(Cash_Flows!H10=0,"n/a",IFERROR(IRR(Cash_Flows!B10:G10),"n/a")) | D5: =IF(Cash_Flows!H10=0,"n/a",IFERROR(IF(Cash_Flows!B11>=0,0,MATCH(TRUE,INDEX(Cash_Flows!B11:G11>=0,0),0)-2-INDEX(Cash_Flows!B11:G11,MATCH(TRUE,INDEX(Cash_Flows!B11:G11>=0,0),0)-1)/INDEX(Cash_Flows!B10:G10,MATCH(TRUE,INDEX(Cash_Flows!B11:G11>=0,0),0))),"> 5 years")) | E5: =-Cash_Flows!B10 | F5: =Cash_Flows!H5+Cash_Flows!H6+Cash_Flows!H7 | G5: =-(Cash_Flows!H8+Cash_Flows!H9) | H5: =Inputs!$B$14*Inputs!$B$10
A6: B. Quick wins | B6: =Cash_Flows!B20+NPV(Inputs!$B$6,Cash_Flows!C20:G20) | C6: =IF(Cash_Flows!H20=0,"n/a",IFERROR(IRR(Cash_Flows!B20:G20),"n/a")) | D6: =IF(Cash_Flows!H20=0,"n/a",IFERROR(IF(Cash_Flows!B21>=0,0,MATCH(TRUE,INDEX(Cash_Flows!B21:G21>=0,0),0)-2-INDEX(Cash_Flows!B21:G21,MATCH(TRUE,INDEX(Cash_Flows!B21:G21>=0,0),0)-1)/INDEX(Cash_Flows!B20:G20,MATCH(TRUE,INDEX(Cash_Flows!B21:G21>=0,0),0))),"> 5 years")) | E6: =-Cash_Flows!B20 | F6: =Cash_Flows!H15+Cash_Flows!H16+Cash_Flows!H17 | G6: =-(Cash_Flows!H18+Cash_Flows!H19) | H6: =Inputs!$C$14*Inputs!$B$10
A7: C. Digital + quick wins | B7: =Cash_Flows!B30+NPV(Inputs!$B$6,Cash_Flows!C30:G30) | C7: =IF(Cash_Flows!H30=0,"n/a",IFERROR(IRR(Cash_Flows!B30:G30),"n/a")) | D7: =IF(Cash_Flows!H30=0,"n/a",IFERROR(IF(Cash_Flows!B31>=0,0,MATCH(TRUE,INDEX(Cash_Flows!B31:G31>=0,0),0)-2-INDEX(Cash_Flows!B31:G31,MATCH(TRUE,INDEX(Cash_Flows!B31:G31>=0,0),0)-1)/INDEX(Cash_Flows!B30:G30,MATCH(TRUE,INDEX(Cash_Flows!B31:G31>=0,0),0))),"> 5 years")) | E7: =-Cash_Flows!B30 | F7: =Cash_Flows!H25+Cash_Flows!H26+Cash_Flows!H27 | G7: =-(Cash_Flows!H28+Cash_Flows!H29) | H7: =Inputs!$D$14*Inputs!$B$10
A9: Recommended option (highest NPV) | B9: =INDEX(A5:A7,MATCH(MAX(B5:B7),B5:B7,0))
A10: Recommendation: approve Option B now (fast payback, low risk) and Option C as phase 2, funded from Option B's benefits, if the NPV holds at the sensitivity below.
A13: Sensitivity: NPV (€) by benefit realisation factor
A14: Option | B14: 0.25 | C14: 0.5 | D14: 0.75 | E14: 1
A15: B. Quick wins | B15: =B6+(Cash_Flows!B15+NPV(Inputs!$B$6,Cash_Flows!C15:G15))*(B$14/Inputs!$B$10-1) | C15: =B6+(Cash_Flows!B15+NPV(Inputs!$B$6,Cash_Flows!C15:G15))*(C$14/Inputs!$B$10-1) | D15: =B6+(Cash_Flows!B15+NPV(Inputs!$B$6,Cash_Flows!C15:G15))*(D$14/Inputs!$B$10-1) | E15: =B6+(Cash_Flows!B15+NPV(Inputs!$B$6,Cash_Flows!C15:G15))*(E$14/Inputs!$B$10-1)
A16: C. Digital + quick wins | B16: =B7+(Cash_Flows!B25+NPV(Inputs!$B$6,Cash_Flows!C25:G25))*(B$14/Inputs!$B$10-1) | C16: =B7+(Cash_Flows!B25+NPV(Inputs!$B$6,Cash_Flows!C25:G25))*(C$14/Inputs!$B$10-1) | D16: =B7+(Cash_Flows!B25+NPV(Inputs!$B$6,Cash_Flows!C25:G25))*(D$14/Inputs!$B$10-1) | E16: =B7+(Cash_Flows!B25+NPV(Inputs!$B$6,Cash_Flows!C25:G25))*(E$14/Inputs!$B$10-1)

Sheet Inputs
A1: Business Case Inputs: SME Loan Origination Redesign
A2: Harbour Bank Ireland (fictional). Blue = input; yellow = key assumption. Source column documents every number.
A4: Input | B4: A. Do nothing | C4: B. Quick wins | D4: C. Digital + quick wins | E4: Source / rationale
A5: GENERAL
A6: Discount rate (annual) | B6: 0.08 | E6: Bank hurdle rate for change projects (assumption).
A7: Average funded loan (€) | B7: 91208 | E7: Process analysis: mean amount of funded applications.
A8: Net margin per year on a funded loan | B8: 0.018 | E8: After funding cost, expected credit loss and servicing (assumption).
A9: Average loan life (years) | B9: 3 | E9: SME term loans 1 to 7 years; average outstanding life (assumption).
A10: Benefit realisation factor | B10: 0.5 | E10: Only half of the modelled extra loans are counted, for prudence.
A11: Underwriter cost per hour (€) | B11: 55 | E11: Fully loaded cost (assumption).
A12: Relationship manager cost per hour (€) | B12: 45 | E12: Fully loaded cost (assumption).
A13: VOLUMES (per year)
A14: Extra funded loans vs today (modelled) | B14: 0 | C14: 455 | D14: 685 | E14: Process analysis notebook, section 5: fewer withdrawals from faster decisions and complete applications.
A15: Credit assessments | B15: 5642 | C15: 5642 | D15: 5642 | E15: Event log, last 12 months.
A16: Document requests (today) | B16: 3883 | C16: 3883 | D16: 3883 | E16: Event log, last 12 months.
A17: EFFICIENCY
A18: Minutes re-keying financials per assessment | B18: 45 | C18: 45 | D18: 45 | E18: Time study with underwriters (workshop estimate).
A19: Reduction in re-keying | B19: 0 | C19: 0 | D19: 0.8 | E19: C: open banking / accounting-software data feed replaces manual spreading.
A20: Minutes of RM time per document request | B20: 40 | C20: 40 | D20: 40 | E20: RM workshop estimate (call, email, chase, check).
A21: Reduction in document requests | B21: 0 | C21: 0.5 | D21: 0.8 | E21: B: digital checklist & upload. C: plus pre-filled data via open banking.
A22: COSTS (€)
A23: One-off cost: year 0 | B23: 0 | C23: 450000 | D23: 1500000 | E23: B: policy change, checklist, portal config, training. C: adds platform build.
A24: One-off cost: year 1 | B24: 0 | C24: 0 | D24: 900000 | E24: C: integration and migration in year 1.
A25: Annual run cost (from year 1) | B25: 0 | C25: 120000 | D25: 380000 | E25: Licences, support, credit forum time.
A26: RAMP-UP of benefits
A27: Year 1 | B27: 0 | C27: 0.5 | D27: 0.25 | E27: Share of full benefit achieved.
A28: Year 2 | B28: 0 | C28: 1 | D28: 0.75
A29: Year 3 | B29: 0 | C29: 1 | D29: 1
A30: Year 4 | B30: 0 | C30: 1 | D30: 1
A31: Year 5 | B31: 0 | C31: 1 | D31: 1

Sheet Cash_Flows
A1: Five-Year Cash Flows by Option (€)
A2: All cells are formulas on the Inputs sheet.
A4: A. Do nothing | B4: Year 0 | C4: Year 1 | D4: Year 2 | E4: Year 3 | F4: Year 4 | G4: Year 5 | H4: Total
A5: Revenue benefit: extra loans funded | B5: =0 | C5: =Inputs!$B$14*Inputs!$B$10*Inputs!$B$27*Inputs!$B$7*Inputs!$B$8*Inputs!$B$9 | D5: =Inputs!$B$14*Inputs!$B$10*Inputs!$B$28*Inputs!$B$7*Inputs!$B$8*Inputs!$B$9 | E5: =Inputs!$B$14*Inputs!$B$10*Inputs!$B$29*Inputs!$B$7*Inputs!$B$8*Inputs!$B$9 | F5: =Inputs!$B$14*Inputs!$B$10*Inputs!$B$30*Inputs!$B$7*Inputs!$B$8*Inputs!$B$9 | G5: =Inputs!$B$14*Inputs!$B$10*Inputs!$B$31*Inputs!$B$7*Inputs!$B$8*Inputs!$B$9 | H5: =SUM(B5:G5)
A6: Efficiency: underwriter re-keying saved | B6: =0 | C6: =Inputs!$B$15*Inputs!$B$18/60*Inputs!$B$19*Inputs!$B$11*Inputs!$B$27 | D6: =Inputs!$B$15*Inputs!$B$18/60*Inputs!$B$19*Inputs!$B$11*Inputs!$B$28 | E6: =Inputs!$B$15*Inputs!$B$18/60*Inputs!$B$19*Inputs!$B$11*Inputs!$B$29 | F6: =Inputs!$B$15*Inputs!$B$18/60*Inputs!$B$19*Inputs!$B$11*Inputs!$B$30 | G6: =Inputs!$B$15*Inputs!$B$18/60*Inputs!$B$19*Inputs!$B$11*Inputs!$B$31 | H6: =SUM(B6:G6)
A7: Efficiency: RM document chasing saved | B7: =0 | C7: =Inputs!$B$16*Inputs!$B$21*Inputs!$B$20/60*Inputs!$B$12*Inputs!$B$27 | D7: =Inputs!$B$16*Inputs!$B$21*Inputs!$B$20/60*Inputs!$B$12*Inputs!$B$28 | E7: =Inputs!$B$16*Inputs!$B$21*Inputs!$B$20/60*Inputs!$B$12*Inputs!$B$29 | F7: =Inputs!$B$16*Inputs!$B$21*Inputs!$B$20/60*Inputs!$B$12*Inputs!$B$30 | G7: =Inputs!$B$16*Inputs!$B$21*Inputs!$B$20/60*Inputs!$B$12*Inputs!$B$31 | H7: =SUM(B7:G7)
A8: One-off costs | B8: =-Inputs!$B$23 | C8: =-Inputs!$B$24 | D8: =0 | E8: =0 | F8: =0 | G8: =0 | H8: =SUM(B8:G8)
A9: Run costs | B9: =0 | C9: =-Inputs!$B$25 | D9: =-Inputs!$B$25 | E9: =-Inputs!$B$25 | F9: =-Inputs!$B$25 | G9: =-Inputs!$B$25 | H9: =SUM(B9:G9)
A10: Net cash flow | B10: =SUM(B5:B9) | C10: =SUM(C5:C9) | D10: =SUM(D5:D9) | E10: =SUM(E5:E9) | F10: =SUM(F5:F9) | G10: =SUM(G5:G9) | H10: =SUM(H5:H9)
A11: Cumulative cash flow | B11: =B10 | C11: =B11+C10 | D11: =C11+D10 | E11: =D11+E10 | F11: =E11+F10 | G11: =F11+G10
A14: B. Quick wins | B14: Year 0 | C14: Year 1 | D14: Year 2 | E14: Year 3 | F14: Year 4 | G14: Year 5 | H14: Total
A15: Revenue benefit: extra loans funded | B15: =0 | C15: =Inputs!$C$14*Inputs!$B$10*Inputs!$C$27*Inputs!$B$7*Inputs!$B$8*Inputs!$B$9 | D15: =Inputs!$C$14*Inputs!$B$10*Inputs!$C$28*Inputs!$B$7*Inputs!$B$8*Inputs!$B$9 | E15: =Inputs!$C$14*Inputs!$B$10*Inputs!$C$29*Inputs!$B$7*Inputs!$B$8*Inputs!$B$9 | F15: =Inputs!$C$14*Inputs!$B$10*Inputs!$C$30*Inputs!$B$7*Inputs!$B$8*Inputs!$B$9 | G15: =Inputs!$C$14*Inputs!$B$10*Inputs!$C$31*Inputs!$B$7*Inputs!$B$8*Inputs!$B$9 | H15: =SUM(B15:G15)
A16: Efficiency: underwriter re-keying saved | B16: =0 | C16: =Inputs!$C$15*Inputs!$C$18/60*Inputs!$C$19*Inputs!$B$11*Inputs!$C$27 | D16: =Inputs!$C$15*Inputs!$C$18/60*Inputs!$C$19*Inputs!$B$11*Inputs!$C$28 | E16: =Inputs!$C$15*Inputs!$C$18/60*Inputs!$C$19*Inputs!$B$11*Inputs!$C$29 | F16: =Inputs!$C$15*Inputs!$C$18/60*Inputs!$C$19*Inputs!$B$11*Inputs!$C$30 | G16: =Inputs!$C$15*Inputs!$C$18/60*Inputs!$C$19*Inputs!$B$11*Inputs!$C$31 | H16: =SUM(B16:G16)
A17: Efficiency: RM document chasing saved | B17: =0 | C17: =Inputs!$C$16*Inputs!$C$21*Inputs!$C$20/60*Inputs!$B$12*Inputs!$C$27 | D17: =Inputs!$C$16*Inputs!$C$21*Inputs!$C$20/60*Inputs!$B$12*Inputs!$C$28 | E17: =Inputs!$C$16*Inputs!$C$21*Inputs!$C$20/60*Inputs!$B$12*Inputs!$C$29 | F17: =Inputs!$C$16*Inputs!$C$21*Inputs!$C$20/60*Inputs!$B$12*Inputs!$C$30 | G17: =Inputs!$C$16*Inputs!$C$21*Inputs!$C$20/60*Inputs!$B$12*Inputs!$C$31 | H17: =SUM(B17:G17)
A18: One-off costs | B18: =-Inputs!$C$23 | C18: =-Inputs!$C$24 | D18: =0 | E18: =0 | F18: =0 | G18: =0 | H18: =SUM(B18:G18)
A19: Run costs | B19: =0 | C19: =-Inputs!$C$25 | D19: =-Inputs!$C$25 | E19: =-Inputs!$C$25 | F19: =-Inputs!$C$25 | G19: =-Inputs!$C$25 | H19: =SUM(B19:G19)
A20: Net cash flow | B20: =SUM(B15:B19) | C20: =SUM(C15:C19) | D20: =SUM(D15:D19) | E20: =SUM(E15:E19) | F20: =SUM(F15:F19) | G20: =SUM(G15:G19) | H20: =SUM(H15:H19)
A21: Cumulative cash flow | B21: =B20 | C21: =B21+C20 | D21: =C21+D20 | E21: =D21+E20 | F21: =E21+F20 | G21: =F21+G20
A24: C. Digital + quick wins | B24: Year 0 | C24: Year 1 | D24: Year 2 | E24: Year 3 | F24: Year 4 | G24: Year 5 | H24: Total
A25: Revenue benefit: extra loans funded | B25: =0 | C25: =Inputs!$D$14*Inputs!$B$10*Inputs!$D$27*Inputs!$B$7*Inputs!$B$8*Inputs!$B$9 | D25: =Inputs!$D$14*Inputs!$B$10*Inputs!$D$28*Inputs!$B$7*Inputs!$B$8*Inputs!$B$9 | E25: =Inputs!$D$14*Inputs!$B$10*Inputs!$D$29*Inputs!$B$7*Inputs!$B$8*Inputs!$B$9 | F25: =Inputs!$D$14*Inputs!$B$10*Inputs!$D$30*Inputs!$B$7*Inputs!$B$8*Inputs!$B$9 | G25: =Inputs!$D$14*Inputs!$B$10*Inputs!$D$31*Inputs!$B$7*Inputs!$B$8*Inputs!$B$9 | H25: =SUM(B25:G25)
A26: Efficiency: underwriter re-keying saved | B26: =0 | C26: =Inputs!$D$15*Inputs!$D$18/60*Inputs!$D$19*Inputs!$B$11*Inputs!$D$27 | D26: =Inputs!$D$15*Inputs!$D$18/60*Inputs!$D$19*Inputs!$B$11*Inputs!$D$28 | E26: =Inputs!$D$15*Inputs!$D$18/60*Inputs!$D$19*Inputs!$B$11*Inputs!$D$29 | F26: =Inputs!$D$15*Inputs!$D$18/60*Inputs!$D$19*Inputs!$B$11*Inputs!$D$30 | G26: =Inputs!$D$15*Inputs!$D$18/60*Inputs!$D$19*Inputs!$B$11*Inputs!$D$31 | H26: =SUM(B26:G26)
A27: Efficiency: RM document chasing saved | B27: =0 | C27: =Inputs!$D$16*Inputs!$D$21*Inputs!$D$20/60*Inputs!$B$12*Inputs!$D$27 | D27: =Inputs!$D$16*Inputs!$D$21*Inputs!$D$20/60*Inputs!$B$12*Inputs!$D$28 | E27: =Inputs!$D$16*Inputs!$D$21*Inputs!$D$20/60*Inputs!$B$12*Inputs!$D$29 | F27: =Inputs!$D$16*Inputs!$D$21*Inputs!$D$20/60*Inputs!$B$12*Inputs!$D$30 | G27: =Inputs!$D$16*Inputs!$D$21*Inputs!$D$20/60*Inputs!$B$12*Inputs!$D$31 | H27: =SUM(B27:G27)
A28: One-off costs | B28: =-Inputs!$D$23 | C28: =-Inputs!$D$24 | D28: =0 | E28: =0 | F28: =0 | G28: =0 | H28: =SUM(B28:G28)
A29: Run costs | B29: =0 | C29: =-Inputs!$D$25 | D29: =-Inputs!$D$25 | E29: =-Inputs!$D$25 | F29: =-Inputs!$D$25 | G29: =-Inputs!$D$25 | H29: =SUM(B29:G29)
A30: Net cash flow | B30: =SUM(B25:B29) | C30: =SUM(C25:C29) | D30: =SUM(D25:D29) | E30: =SUM(E25:E29) | F30: =SUM(F25:F29) | G30: =SUM(G25:G29) | H30: =SUM(H25:H29)
A31: Cumulative cash flow | B31: =B30 | C31: =B31+C30 | D31: =C31+D30 | E31: =D31+E30 | F31: =E31+F30 | G31: =F31+G30
